{
  "limit" : 20,
  "offset" : 0,
  "count" : 2,
  "total" : 2,
  "results" : [
    {
      "id" : "8406af27-e9ce-43a3-8430-fefbbd8dc70f",
      "version" : 1,
      "createdAt" : "2022-03-04T11:28:21.623Z",
      "lastModifiedAt" : "2022-03-04T11:28:21.623Z",
      "lastModifiedBy" : {
        "clientId" : "THGlCWh5D1WjiTOzlZedcEx4",
        "isPlatformClient" : false
      },
      "createdBy" : {
        "clientId" : "THGlCWh5D1WjiTOzlZedcEx4",
        "isPlatformClient" : false
      },
      "name" : {
        "en" : "Sample name 1"
      },
      "description" : {
        "en" : "Sample description 2"
      },
      "key" : "group-x",
      "attributes" : [
        { "key" : "Attribute x1" },
        { "key" : "Attribute x2" }
      ]
    },
    {
      "id" : "e109bb14-f2b4-451a-a44c-8e4755705607",
      "version" : 1,
      "createdAt" : "2022-03-04T11:28:21.675Z",
      "lastModifiedAt" : "2022-03-04T11:28:21.675Z",
      "lastModifiedBy" : {
        "clientId" : "THGlCWh5D1WjiTOzlZedcEx4",
        "isPlatformClient" : false
      },
      "createdBy" : {
        "clientId" : "THGlCWh5D1WjiTOzlZedcEx4",
        "isPlatformClient" : false
      },
      "name" : {
        "en" : "Sample name 2"
      },
      "description" : {
        "en" : "Sample description 2"
      },
      "key" : "group-y",
      "attributes" : [
        { "key" : "Attribute y1" },
        { "key" : "Attribute y2" }
      ]
    }
  ]
}
