{
    "key":"my-application",
    "allowedOrigins": {
       "allowAll": false,
       "origins":[
          "https://demo.com"
       ]
    },
    "countries":["DE"],
    "description":{
       "en":"English description"
    },
    "name":"My Application",
    "mode":"CompleteFlow",
    "status":"Active",
    "logo":{
       "url":"https://svgshare.com/i/120g.svg"
    },
    "agreements":[
       {
          "id":"bc95d35a-8cc1-484c-b207-bd8c55a55a28",
          "name":"myAgreement",
          "type":"MandatoryCheckbox",
          "status":"Active",
          "text":{
             "en":"By clicking the Complete Purchase button below, I agree to the Terms of Use."
          }
 
       }
    ],
    "paymentsConfiguration": {
      "paymentReturnUrl":"https://demo.com/checkout",
      "activePaymentComponentType":"Component"
    },
   "discountsConfiguration": {
      "allowDiscounts":true
    }
 }