{
  "$schema": "http://json-schema.org/draft-04/schema#",

  "title": "Error",
  "type": "object",

  "required": ["statusCode", "message"],

  "properties": {
    "statusCode": {
      "type": "number",
      "description": "The same HTTP status code used in the response"
    },
    "message": {
      "type": "string",
      "description": "Human-readable message"
    },
    "errors": {
      "type": "array",
      "items": {
        "type": "object",
        "oneOf": [{
          "title": "Error",
          "type": "object",
          "required": ["code", "message"],
          "properties": {
            "code": {
              "type": "string",
              "description": "Specific error code"
            },
            "message": {
              "type": "string",
              "description": "Human-readable message"
            }
          }
        },{
          "title": "DuplicatePriceScope",
          "type": "object",
          "description":"A given price scope conflicts with an existing one. Every price of a product variant must have a distinct combination of currency, customer group, country and channel. These four properties constitute the scope of a price.",
          "required": ["code", "message", "conflictingPrices"],
          "properties": {
            "code": {
              "type": "string",
              "description": "Specific error code",
              "enum":["DuplicatePriceScope"]
            },
            "message": {
              "type": "string",
              "description": "Human-readable message"
            },
            "conflictingPrices":{
              "type": "array",
              "items": {
                "$ref":"price.schema.json"
              }
            }
          }
        },{
          "title": "DuplicateVariantValues",
          "type": "object",
          "required": ["code", "message", "variantValues"],
          "description": "A given combination of variant values conflicts with an existing one. Every product variant must have a distinct combination of SKU, prices, and custom attribute values.",
          "properties": {
            "code": {
              "type": "string",
              "description": "Specific error code",
              "enum":["DuplicateVariantValues"]
            },
            "message": {
              "type": "string",
              "description": "Human-readable message"
            },
            "variantValues":{
              "$ref":"variant-values.schema.json"
            }
          }
        },{
          "title": "DuplicateAttributeValue",
          "type": "object",
          "required": ["code", "message", "attribute"],
          "description": "The Unique AttributeConstraint was violated.",
          "properties": {
            "code": {
              "type": "string",
              "description": "Specific error code",
              "enum":["DuplicateAttributeValue"]
            },
            "message": {
              "type": "string",
              "description": "Human-readable message"
            },
            "attribute":{
              "$ref":"attribute.schema.json"
            }
          }
        },{
          "title": "DuplicateAttributeValues",
          "type": "object",
          "required": ["code", "message", "attributes"],
          "description": "The CombinationUnique AttributeConstraint was violated.",
          "properties": {
            "code": {
              "type": "string",
              "description": "Specific error code",
              "enum":["DuplicateAttributeValues"]
            },
            "message": {
              "type": "string",
              "description": "Human-readable message"
            },
            "attributes":{
              "type": "array",
              "items": {
                "$ref":"attribute.schema.json"
              }
            }
          }
        }
      ]
      }
    }
  }
}
